gbooks_upload/__init__.py
gbooks_upload/const.py
gbooks_upload/drive.py
gbooks_upload/endpoints.py
gbooks_upload/py.typed
gbooks_upload/scotty.py
gbooks_upload-0.7.1.data/data/share/man/man1/gbooks-upload-books-get.1
gbooks_upload-0.7.1.data/data/share/man/man1/gbooks-upload-books-list.1
gbooks_upload-0.7.1.data/data/share/man/man1/gbooks-upload-books.1
gbooks_upload-0.7.1.data/data/share/man/man1/gbooks-upload-login.1
gbooks_upload-0.7.1.data/data/share/man/man1/gbooks-upload-rpc.1
gbooks_upload-0.7.1.data/data/share/man/man1/gbooks-upload-shelves-add.1
gbooks_upload-0.7.1.data/data/share/man/man1/gbooks-upload-shelves-list.1
gbooks_upload-0.7.1.data/data/share/man/man1/gbooks-upload-shelves.1
gbooks_upload-0.7.1.data/data/share/man/man1/gbooks-upload-steal.1
gbooks_upload-0.7.1.data/data/share/man/man1/gbooks-upload-upload.1
gbooks_upload-0.7.1.data/data/share/man/man1/gbooks-upload.1
gbooks_upload-0.7.1.dist-info/LICENSE
gbooks_upload-0.7.1.dist-info/METADATA
gbooks_upload-0.7.1.dist-info/WHEEL
gbooks_upload-0.7.1.dist-info/entry_points.txt
gbooks_upload-0.7.1.dist-info/top_level.txt
gbooks_upload-0.7.1.dist-info/RECORD
